Workbook

Sheet Planilha1
A3: Emprendimento | B3: Orçamento | C3: VGV | D3: Venda efetuadas | E3: Saldo Vendas
A4: SUNSET | B4: 25209649 | C4: 28091456 | D4: 22507979 | E4: =C4-D4 -> 5583476.4
A5: PHAROS | B5: 22774123 | C5: 35108308 | D5: 25536380 | E5: =C5-D5 -> 9571927.2
F10: RESUMO | G10: RECEITA | H10: % Vendas Efetuadas | I10: DESPESA | J10: % Gasto do orçamento
A11: Empreendimentos | B11: Período | C11: RECEITAS | D11: DESPESAS | F11: SUNSET | G11: =SUM(C12:C34) -> 10606741 | H11: =G11/D4 -> 0.47124359 | I11: =SUM(D12:D34) -> 7799619.7 | J11: =I11/B4 -> 0.30939025
A12: SUNSET | B12: 45261 | C12: 151140.77 | D12: 0 | F12: PHAROS | G12: =SUM(C35:C54) -> 6286653.5 | H12: =G12/D5 -> 0.24618421 | I12: =SUM(D35:D54) -> 5119915 | J12: =I12/B5 -> 0.22481283
A13: SUNSET | B13: 45292 | C13: 227253.58 | D13: 15690.23
A14: SUNSET | B14: 45323 | C14: 212865.3 | D14: 10000
A15: SUNSET | B15: 45352 | C15: 211083.78 | D15: 3530
A16: SUNSET | B16: 45383 | C16: 218541.92 | D16: 4332.29
A17: SUNSET | B17: 45413 | C17: 332451.75 | D17: 17188.97
A18: SUNSET | B18: 45444 | C18: 746103.78 | D18: 24201.68
A19: SUNSET | B19: 45474 | C19: 407428.33 | D19: 60305.97
A20: SUNSET | B20: 45505 | C20: 849977.69 | D20: 384068.3
A21: SUNSET | B21: 45536 | C21: 229129.49 | D21: 120397.96
A22: SUNSET | B22: 45566 | C22: 323825.42 | D22: 118839.31
A23: SUNSET | B23: 45597 | C23: 286102.73 | D23: 190074.19
A24: SUNSET | B24: 45627 | C24: 738681.77 | D24: 157929.09
... A54: PHAROS | B54: 45931 | C54: 378373.54 | D54: 398370.62

Sheet Planilha2
C2: Prazo final obra | D2: Saldo dos Valores Vendidos | E2: Saldo Vendas
A3: Emprendimento | B3: Saldo orçamentário
A4: SUNSET | B4: =Planilha1!B4-Planilha1!I11 -> 17410029 | C4: 46722 | D4: =Planilha1!D4-Planilha1!G11 -> 11901238 | E4: =Planilha1!E4 -> 5583476.4 | F4: =D4-B4 -> -5508790.9
A5: PHAROS | B5: =Planilha1!B5-Planilha1!I12 -> 17654208 | C5: 46722 | D5: =Planilha1!D5-Planilha1!G12 -> 19249727 | E5: =Planilha1!E5 -> 9571927.2 | F5: =D5-B5 -> 1595519.2
AG6: =B4/26 -> 669616.51
C7: 45962 | D7: 45992 | E7: 46023 | F7: 46054 | G7: 46082 | H7: 46113 | I7: 46143 | J7: 46174 | K7: 46204 | L7: 46235 | M7: 46266 | N7: 46296 | O7: 46327 | P7: 46357 | Q7: 46388 | R7: 46419 | S7: 46447 | T7: 46478 | U7: 46508 | V7: 46539 | W7: 46569 | X7: 46600 | Y7: 46631 | Z7: 46661 | AA7: 46692 | AB7: 46722 | AG7: =D4/26 -> 457739.94
A8: SUNSET | B8: RECEITA PROJETADA | C8: 457739.94 | D8: 457739.94 | E8: 457739.94 | F8: 457739.94 | G8: 457739.94 | H8: 457739.94 | I8: 457739.94 | J8: 457739.94 | K8: 457739.94 | L8: 457739.94 | M8: 457739.94 | N8: 457739.94 | O8: 457739.94 | P8: 457739.94 | Q8: 457739.94 | R8: 457739.94 | S8: 457739.94 | T8: 457739.94 | U8: 457739.94 | V8: 457739.94 | W8: 457739.94 | X8: 457739.94 | Y8: 457739.94 | Z8: 457739.94 | AA8: 457739.94 | AB8: 457739.94
B9: DESPESA PROJETADA | C9: 669616.51 | D9: 669616.51 | E9: 669616.51 | F9: 669616.51 | G9: 669616.51 | H9: 669616.51 | I9: 669616.51 | J9: 669616.51 | K9: 669616.51 | L9: 669616.51 | M9: 669616.51 | N9: 669616.51 | O9: 669616.51 | P9: 669616.51 | Q9: 669616.51 | R9: 669616.51 | S9: 669616.51 | T9: 669616.51 | U9: 669616.51 | V9: 669616.51 | W9: 669616.51 | X9: 669616.51 | Y9: 669616.51 | Z9: 669616.51 | AA9: 669616.51 | AB9: 669616.51 | AG9: =B5/26 -> 679007.98
AG10: =D5/26 -> 740374.11
C15: 45962 | D15: 45992 | E15: 46023 | F15: 46054 | G15: 46082 | H15: 46113 | I15: 46143 | J15: 46174 | K15: 46204 | L15: 46235 | M15: 46266 | N15: 46296 | O15: 46327 | P15: 46357 | Q15: 46388 | R15: 46419 | S15: 46447 | T15: 46478 | U15: 46508 | V15: 46539 | W15: 46569 | X15: 46600 | Y15: 46631 | Z15: 46661 | AA15: 46692 | AB15: 46722
A16: PHAROS | B16: RECEITA PROJETADA | C16: 740374.11 | D16: 740374.11 | E16: 740374.11 | F16: 740374.11 | G16: 740374.11 | H16: 740374.11 | I16: 740374.11 | J16: 740374.11 | K16: 740374.11 | L16: 740374.11 | M16: 740374.11 | N16: 740374.11 | O16: 740374.11 | P16: 740374.11 | Q16: 740374.11 | R16: 740374.11 | S16: 740374.11 | T16: 740374.11 | U16: 740374.11 | V16: 740374.11 | W16: 740374.11 | X16: 740374.11 | Y16: 740374.11 | Z16: 740374.11 | AA16: 740374.11 | AB16: 740374.11
B17: DESPESA PROJETADA | C17: 679007.98 | D17: 679007.98 | E17: 679007.98 | F17: 679007.98 | G17: 679007.98 | H17: 679007.98 | I17: 679007.98 | J17: 679007.98 | K17: 679007.98 | L17: 679007.98 | M17: 679007.98 | N17: 679007.98 | O17: 679007.98 | P17: 679007.98 | Q17: 679007.98 | R17: 679007.98 | S17: 679007.98 | T17: 679007.98 | U17: 679007.98 | V17: 679007.98 | W17: 679007.98 | X17: 679007.98 | Y17: 679007.98 | Z17: 679007.98 | AA17: 679007.98 | AB17: 679007.98
